odoo/__init__.py
odoo/addons/__init__.py
odoo/addons/ras2/__init__.py
odoo/addons/ras2/__manifest__.py
odoo/addons/ras2/models/__init__.py
odoo/addons/ras2/models/hr_employee.py
odoo/addons/ras2/tests/__init__.py
odoo/addons/ras2/tests/test_t_hr_attendance_rfid_process.py
odoo12_addon_ras2-12.0.1.0.11.dist-info/DESCRIPTION.rst
odoo12_addon_ras2-12.0.1.0.11.dist-info/METADATA
odoo12_addon_ras2-12.0.1.0.11.dist-info/RECORD
odoo12_addon_ras2-12.0.1.0.11.dist-info/WHEEL
odoo12_addon_ras2-12.0.1.0.11.dist-info/metadata.json
odoo12_addon_ras2-12.0.1.0.11.dist-info/top_level.txt
