Metadata-Version: 2.0
Name: odoo12-addon-ras2
Version: 12.0.1.0.11
Summary: RFID Attendance System RAS2 v12.0.1.0.10
Home-page: https://github.com/thingsintouch/attendance
Author: thingsintouch.com,
License: AGPL-3
Platform: UNKNOWN
Classifier: Programming Language :: Python
Classifier: Framework :: Odoo
Classifier: License :: OSI Approved :: GNU Affero General Public License v3
Requires-Python: >=3.5
Requires-Dist: odoo12-addon-hr-attendance-rfid (==12.0.1.1.0.99.dev1)
Requires-Dist: odoo (<12.1dev,>=12.0a)
